setup.py
prob/__init__.py
prob/counter.py
prob.egg-info/PKG-INFO
prob.egg-info/SOURCES.txt
prob.egg-info/dependency_links.txt
prob.egg-info/top_level.txt
tests/__init__.py
tests/test_counter.py