Metadata-Version: 1.0
Name: prob
Version: 0.0.2
Summary: Utilities for creating and working with discreteprobability distributions
Home-page: http://github.com/nuance/prob
Author: Matt Jones
Author-email: oss@mhjones.org
License: BSD
Keywords: probability
Platform: UNKNOWN
Classifier: Development Status :: 3 - Alpha
Classifier: Topic :: Scientific/Engineering :: Mathematics
Classifier: Topic :: Scientific/Engineering :: Artificial Intelligence
Classifier: License :: OSI Approved :: BSD License
